obsidian_notion_sync/__about__.py
obsidian_notion_sync/__init__.py
obsidian_notion_sync/_version.py
obsidian_notion_sync/cli.py
obsidian_notion_sync/config.py
obsidian_notion_sync/exceptions.py
obsidian_notion_sync/sync.py
obsidian_notion_sync/sync_to_notion.py
obsidian_notion_sync-0.7.dist-info/METADATA
obsidian_notion_sync-0.7.dist-info/WHEEL
obsidian_notion_sync-0.7.dist-info/entry_points.txt
obsidian_notion_sync-0.7.dist-info/RECORD
