Metadata-Version: 2.3
Name: obsidian-notion-sync
Version: 0.7
Summary: Sync Obsidian notes to Notion via GitHub
Project-URL: Documentation, https://github.com/Akash-Sharma-1/obsidian-notion-sync
Project-URL: Issues, https://github.com/Akash-Sharma-1/obsidian-notion-sync/issues
Project-URL: Source, https://github.com/Akash-Sharma-1/obsidian-notion-sync
Author-email: Akash Sharma <howdy.akash@gmail.com>
License-Expression: MIT
Classifier: Development Status :: 4 - Beta
Classifier: Intended Audience :: Developers
Classifier: License :: OSI Approved :: MIT License
Classifier: Programming Language :: Python :: 3
Classifier: Programming Language :: Python :: 3.7
Classifier: Programming Language :: Python :: 3.8
Classifier: Programming Language :: Python :: 3.9
Classifier: Programming Language :: Python :: 3.10
Requires-Python: >=3.7
Requires-Dist: click>=8.0.0
Requires-Dist: markdown2>=2.4.0
Requires-Dist: notion-client>=1.0.0
Requires-Dist: pygithub>=1.55
Requires-Dist: requests>=2.25.0
